oligoMass/ElementsTable.py
oligoMass/__init__.py
oligoMass/dna.py
oligoMass/exModifications.py
oligoMass/molmassOligo.py
oligoMass-0.2.0.dist-info/METADATA
oligoMass-0.2.0.dist-info/WHEEL
oligoMass-0.2.0.dist-info/top_level.txt
oligoMass-0.2.0.dist-info/RECORD
