Metadata-Version: 2.1
Name: oligoMass
Version: 0.2.0
Requires-Dist: molmass
Requires-Dist: pandas
